auto/__init__.py
happylife-1.8.0.dist-info/METADATA
happylife-1.8.0.dist-info/WHEEL
happylife-1.8.0.dist-info/top_level.txt
happylife-1.8.0.dist-info/RECORD
