Metadata-Version: 2.1
Name: happylife
Version: 1.8.0
Summary: 圖色識別，自動操作滑鼠/鍵盤(可後臺運行)，將一切重複的事，抽象為函數，自動運行。
Author: 宇宙中的塵埃
Author-email: yqnacfmh9@gmail.com
Requires-Dist: numpy==2.0.1
Requires-Dist: opencv-python==4.11.0.86
Requires-Dist: Pillow==11.3.0
Requires-Dist: pywin32==310
